Metadata-Version: 2.1
Name: resnet-ai
Version: 0.6
Summary: ResNet AI functions
Home-page: UNKNOWN
Author: Alberto Saenz
Author-email: alberto.saenz@resnet.ai
License: UNKNOWN
Platform: UNKNOWN
